README.md
setup.cfg
setup.py
dynamixel_controller.egg-info/PKG-INFO
dynamixel_controller.egg-info/SOURCES.txt
dynamixel_controller.egg-info/dependency_links.txt
dynamixel_controller.egg-info/requires.txt
dynamixel_controller.egg-info/top_level.txt
dynamixel_sdk/__init__.py
dynamixel_sdk/group_bulk_read.py
dynamixel_sdk/group_bulk_write.py
dynamixel_sdk/group_sync_read.py
dynamixel_sdk/group_sync_write.py
dynamixel_sdk/packet_handler.py
dynamixel_sdk/port_handler.py
dynamixel_sdk/protocol1_packet_handler.py
dynamixel_sdk/protocol2_packet_handler.py
dynamixel_sdk/robotis_def.py
dynio/__init__.py
dynio/dynamixel_controller.py
dynio/DynamixelJSON/AX12.json
dynio/DynamixelJSON/MX106.json
dynio/DynamixelJSON/MX12.json
dynio/DynamixelJSON/MX28.json
dynio/DynamixelJSON/MX64.json
dynio/DynamixelJSON/__init__.py