Metadata-Version: 2.1
Name: dynamixel-controller
Version: 0.9.0
Summary: A new tool for operating Dynamixel series motors!
Home-page: https://github.com/UGA-BSAIL/dynamixel-controller
Author: Hunter Halloran (Jyumpp)
Author-email: hdh20267@uga.edu
License: UNKNOWN
Download-URL: https://github.com/UGA-BSAIL/dynamixel-controller/archive/dynamixel_controller-0.9.0.tar.gz
Keywords: dynamixel,dxl,dynamixel_sdk,motor controller,robotis,motor,robot
Platform: UNKNOWN
Classifier: Development Status :: 4 - Beta
Classifier: Intended Audience :: Developers
Classifier: Topic :: Software Development :: Libraries
Classifier: License :: OSI Approved :: Apache Software License
Classifier: Programming Language :: Python :: 2
Classifier: Programming Language :: Python :: 2.7
Classifier: Programming Language :: Python :: 3
Classifier: Programming Language :: Python :: 3.4
Classifier: Programming Language :: Python :: 3.5
Classifier: Programming Language :: Python :: 3.6
Classifier: Programming Language :: Python :: 3.7
Classifier: Programming Language :: Python :: 3.8
